{
    "id": 6,
    "title": "Хитрости складного",
    "image": "images/lifehacks/list/6.webp",
    "tags": ["виды велосипедов"],
    "parts": [
        {
            "title": "Шарниры",
            "text": "Со временем начинают скрипеть или закусывать. Раз в пару недель требуется капля смазки на шарнир и защёлку. "
        },
        {
            "title": "Проверка",
            "text": "Перед выездом важно убедиться, что все замки и фиксаторы защёлкнуты. Иначе — люфты и риск сложиться на ходу."
        },
        {
            "title": "Парковка",
            "text": "Велосипедки изготавливаются из дышащих материалов, которые эффективно отводят пот, а нижнее белье из хлопка или синтетики задерживает влагу, создавая ощущение сырости и дискомфорта."
        },
        {
            "title": "Транспортировка",
            "text": "Для удобной переноски — ремень или чехол-рюкзак, особенно в метро или поездах. В сложенном виде велосипед можно везти как чемодан."
        },
        {
            "title": "Обвес",
            "text": "Лишние элементы — вес и неудобство в складывании. Лучше выбирать компактные крылья, съёмные фонари, лёгкие багажники."
        }
    ]
}