{
    "title": "Забытые сады и парки",
    "banner_image": "images/routes/4/cover.webp",
    "description": "Этот маршрут пройдёт через старинные усадьбы и парки, где до сих пор ощущается дух прошлого. По пути встретятся заброшенные аллеи, таинственные лесные тропы и архитектурные памятники, сохранившие атмосферу ушедших эпох. Отличный вариант для тех, кто хочет покататься в тени старых деревьев, открыть для себя малоизвестные места и почувствовать связь с историей.  ",
    "tags": ["прогулка", "парки"],
    "summary": {
        "difficulty": "images/routes/quarks/difficulty-medium.svg",
        "distance": "35 км",
        "time": "3 часа"
    },
    "sections": [
        {
            "id": "Lyublino",
            "title": "Усадьба Люблино",
            "parts": [
                {
                    "type": "text",
                    "value": "Начинаем маршрут в парке усадьбы Люблино. Когда-то здесь находился один из самых роскошных загородных дворцов, а сегодня сохранились лишь его части, окружённые старыми прудами и тенистыми аллеями. Велодорожек здесь нет, но ехать можно по широким прогулочным тропам, наслаждаясь спокойной атмосферой."
                },
                {
                    "type": "image",
                    "value": [
                        "images/routes/4/1.webp",
                        "images/routes/4/2.webp"
                    ]
                },
                {
                    "type": "features",
                    "value": [
                        {
                            "icon": "images/routes/quarks/features/fountain.svg",
                            "text": "зеркальный пруд"
                        },
                        {
                            "icon": "images/routes/quarks/features/forest.svg",
                            "text": "тихий уголок"
                        },
                        {
                            "icon": "images/routes/quarks/features/arcitecture.svg",
                            "text": "историческая архитектура"
                        }
                    ]
                }
            ]
        },
        {
            "id": "Vorontsovo",
            "title": "Парк-усадьба Воронцово",
            "parts": [
                {
                    "type": "text",
                    "value": "Двигаемся в сторону Воронцовского парка — бывшей усадьбы с длинными липовыми аллеями, руинами старых построек и красивыми водоёмами. Это место скрывает множество исторических уголков, где создается ощущение будто время остановилось."
                },
                {
                    "type": "image",
                    "value": [
                        "images/routes/4/3.webp"
                    ]
                },
                {
                    "type": "features",
                    "value": [
                        {
                            "icon": "images/routes/quarks/features/forest.svg",
                            "text": "липовые аллеи"
                        },
                        {
                            "icon": "images/routes/quarks/features/bike.svg",
                            "text": "секретные дорожки"
                        },
                        {
                            "icon": "images/routes/quarks/features/fountain.svg",
                            "text": "уединённые пруды"
                        }
                    ]
                }
            ]
        },
        {
            "id": "Suhanovo",
            "title": "Усадьба Суханово",
            "parts": [
                {
                    "type": "text",
                    "value": "Финальная точка маршрута — усадьба Суханово, одно из самых таинственных мест Подмосковья. Разрушенные корпуса, заросшие дорожки и вековые деревья создают ощущение, что ты попал в другое время. Здесь можно оставить велосипеды и немного прогуляться пешком, чтобы почувствовать всю магию места."
                },
                {
                    "type": "image",
                    "value": [
                        "images/routes/4/4.webp",
                        "images/routes/4/5.webp"
                    ]
                },
                {
                    "type": "features",
                    "value": [
                        {
                            "icon": "images/routes/quarks/features/arcitecture.svg",
                            "text": "полуразрушенные постройки"
                        },
                        {
                            "icon": "images/routes/quarks/features/road.svg",
                            "text": "малолюдные тропы"
                        },
                        {
                            "icon": "images/routes/quarks/features/forest.svg",
                            "text": "старинный лес"
                        }
                    ]
                }
            ]
        }
    ],
    "ending": [
        {
            "title": "Разное покрытие",
            "value": "встречаются участки с грунтовыми тропами, поэтому велосипед лучше выбрать универсальный."
        },
        {
            "title": "Лучшее время",
            "value": "утро или вечер, когда свет делает старинные усадьбы ещё более атмосферными."
        },
        {
            "title": "Темп поездки",
            "value": "неспешный, с остановками, чтобы насладиться видами и лучше ориентироваться на местности."
        }
    ]
}